aiofile_linux/__init__.py
aiofile_linux/aio_context.py
aiofile_linux/aio_event.py
aiofile_linux/py.typed
aiofile_linux/command/__init__.py
aiofile_linux/command/base.py
aiofile_linux/command/non_rw.py
aiofile_linux/command/non_vector.py
aiofile_linux/command/rw.py
aiofile_linux/command/vector.py
aiofile_linux-0.1.0.dist-info/COPYING
aiofile_linux-0.1.0.dist-info/COPYING.LESSER
aiofile_linux-0.1.0.dist-info/METADATA
aiofile_linux-0.1.0.dist-info/WHEEL
aiofile_linux-0.1.0.dist-info/top_level.txt
aiofile_linux-0.1.0.dist-info/RECORD
